TP1 Verilog/ProjetoDeBloco_MesaDeSom/src/digital_mixer.v
module digital_mixer (
    input wire clk,
    input wire rst_n,
    input wire signed [15:0] entrada_1,
    input wire signed [15:0] entrada_2,
    input wire [7:0] vol_ch1,           // Volume 0 = mudo, 128 = 1x, 255 = 2x
    input wire [7:0] vol_ch2,
    output reg signed [15:0] saida_som
);

    reg signed [24:0] mult1;
    reg signed [24:0] mult2;
    reg signed [25:0] sinal_mixado;
    
    wire signed [25:0] escala_saida;
    assign escala_saida = sinal_mixado >>> 7; 

    always @(posedge clk or negedge rst_n) begin
        if (!rst_n) begin
            mult1        <= 25'sd0;
            mult2        <= 25'sd0;
            sinal_mixado <= 26'sd0;
            saida_som    <= 16'sd0;
        end else begin
            mult1 <= entrada_1 * $signed({1'b0, vol_ch1});
            mult2 <= entrada_2 * $signed({1'b0, vol_ch2});
            
            sinal_mixado <= mult1 + mult2;
            
            if (escala_saida > 26'sd32367)
                saida_som <= 16'sd32767;
            else if (escala_saida < -26'sd32768)
                saida_som <= -16'sd32768;
            else
                saida_som <= escala_saida[15:0];
        end
    end
endmodule

TP1 Verilog/ProjetoDeBloco_MesaDeSom/src/tb_digital_mixer.v
`timescale 1ns / 1ps

module tb_digital_mixer;

    reg clk;
    reg rst_n;
    reg signed [15:0] entrada_1;
    reg signed [15:0] entrada_2;
    reg [7:0] vol_ch1;
    reg [7:0] vol_ch2;
    wire signed [15:0] saida_som;

    digital_mixer uut (
        .clk(clk),
        .rst_n(rst_n),
        .entrada_1(entrada_1),
        .entrada_2(entrada_2),
        .vol_ch1(vol_ch1),
        .vol_ch2(vol_ch2),
        .saida_som(saida_som)
    );

    // Geração do Clock: Período de 20ns (Equivale a 50 MHz)
    always #10 clk = ~clk;

    initial
    begin
        $dumpfile("testbench_digital.vcd");
        $dumpvars(0, tb_digital_mixer);
        
        clk = 0;
        rst_n = 0;
        entrada_1 = 16'sd0;
        entrada_2 = 16'sd0;
        vol_ch1 = 8'd0;
        vol_ch2 = 8'd0;
        $display("Tempo=%0t | CENARIO 3 | entrada_1 = %d | entrada_2 = %d | vol_ch1 = %d | vol_ch2 = %d | saida_som = %d", $time, entrada_1, entrada_2, vol_ch1, vol_ch2, saida_som);

        //Libera o sistema do reset
        repeat(2) @(posedge clk);
        #2; 
        rst_n = 1;

        //CENARIO 1: Canal 1 com ganho 1.0 (128) e canal 2 Mutado
        entrada_1 = 16'sd5000;  
        entrada_2 = 16'sd12000;
        vol_ch1 = 8'd128;       
        vol_ch2 = 8'd0;         
        //Saída esperada 5000
        repeat(3) @(posedge clk); // Espera a conta ser feita
        #2;
        // Printa manualmente o resultado após o cálculo:
        $display("Tempo=%0t | CENARIO 1 | entrada_1 = %d | entrada_2 = %d | vol_ch1 = %d | vol_ch2 = %d | saida_som = %d", $time, entrada_1, entrada_2, vol_ch1, vol_ch2, saida_som);


        //CENARIO 2: Ambos os canais somados normalmente
        entrada_1 = 16'sd4000;
        entrada_2 = 16'sd6000;
        vol_ch1 = 8'd128;       
        vol_ch2 = 8'd128;       
        //Saída esperada 1000
        repeat(3) @(posedge clk);
        #2;
        $display("Tempo=%0t | CENARIO 2 | entrada_1 = %d | entrada_2 = %d | vol_ch1 = %d | vol_ch2 = %d | saida_som = %d", $time, entrada_1, entrada_2, vol_ch1, vol_ch2, saida_som);


        //CENARIO 3: Teste de Estouro
        entrada_1 = 16'sd30000;
        entrada_2 = 16'sd25000;
        vol_ch1 = 8'd255;       
        vol_ch2 = 8'd255;
        //Saída esperada 32767
        repeat(3) @(posedge clk);
        #2;
        $display("Tempo=%0t | CENARIO 3 | entrada_1 = %d | entrada_2 = %d | vol_ch1 = %d | vol_ch2 = %d | saida_som = %d", $time, entrada_1, entrada_2, vol_ch1, vol_ch2, saida_som);
        
        #100;
        $finish;
    end
endmodule

TP1 Verilog/ProjetoDeBloco_MesaDeSom/src/testbench_digital.vcd
$date
	Sat May 23 15:44:26 2026
$end
$version
	Icarus Verilog
$end
$timescale
	1ps
$end
$scope module tb_digital_mixer $end
$var wire 16 ! saida_som [15:0] $end
$var reg 1 " clk $end
$var reg 16 # entrada_1 [15:0] $end
$var reg 16 $ entrada_2 [15:0] $end
$var reg 1 % rst_n $end
$var reg 8 & vol_ch1 [7:0] $end
$var reg 8 ' vol_ch2 [7:0] $end
$scope module uut $end
$var wire 1 " clk $end
$var wire 16 ( entrada_1 [15:0] $end
$var wire 16 ) entrada_2 [15:0] $end
$var wire 1 % rst_n $end
$var wire 8 * vol_ch1 [7:0] $end
$var wire 8 + vol_ch2 [7:0] $end
$var wire 26 , escala_saida [25:0] $end
$var reg 25 - mult1 [24:0] $end
$var reg 25 . mult2 [24:0] $end
$var reg 16 / saida_som [15:0] $end
$var reg 26 0 sinal_mixado [25:0] $end
$upscope $end
$upscope $end
$enddefinitions $end
$comment Show the parameter values. $end
$dumpall
$end
#0
$dumpvars
b0 0
b0 /
b0 .
b0 -
b0 ,
b0 +
b0 *
b0 )
b0 (
b0 '
b0 &
0%
b0 $
b0 #
0"
b0 !
$end
#10000
1"
#20000
0"
#30000
1"
#32000
b10000000 &
b10000000 *
b10111011100000 $
b10111011100000 )
b1001110001000 #
b1001110001000 (
1%
#40000
0"
#50000
b10011100010000000000 -
1"
#60000
0"
#70000
b1001110001000 ,
b10011100010000000000 0
1"
#80000
0"
#90000
b1001110001000 !
b1001110001000 /
1"
#92000
b10000000 '
b10000000 +
b1011101110000 $
b1011101110000 )
b111110100000 #
b111110100000 (
#100000
0"
#110000
b10111011100000000000 .
b1111101000000000000 -
1"
#120000
0"
#130000
b10011100010000 ,
b100111000100000000000 0
1"
#140000
0"
#150000
b10011100010000 !
b10011100010000 /
1"
#152000
b11111111 '
b11111111 +
b11111111 &
b11111111 *
b110000110101000 $
b110000110101000 )
b111010100110000 #
b111010100110000 (
#160000
0"
#170000
b11000010100011001011000 .
b11101001011101011010000 -
1"
#180000
0"
#190000
b11010110000000010 ,
b110101100000000100101000 0
1"
#200000
0"
#210000
b111111111111111 !
b111111111111111 /
1"
